xingpypitest/__init__.py
xingpypitest/foo.py
xingpypitest/pkg/__init__.py
xingpypitest/pkg/bar.py
xingpypitest-0.0.5.dist-info/METADATA
xingpypitest-0.0.5.dist-info/WHEEL
xingpypitest-0.0.5.dist-info/top_level.txt
xingpypitest-0.0.5.dist-info/RECORD
