Metadata-Version: 2.1
Name: xingpypitest
Version: 0.0.5
Summary: The Short Description
Home-page: http://www.baidu.com
Author: XING-ZIWEN
Author-email: Rick.Xing@Nachmath.com
License: UNKNOWN
Platform: UNKNOWN
Classifier: Programming Language :: Python :: 3
Classifier: License :: OSI Approved :: MIT License
Classifier: Development Status :: 2 - Pre-Alpha
Classifier: Intended Audience :: Developers
Requires-Python: >=3.6
